src/__init__.py
src/dataset_creator.py
src/image_processing.py
src/training.py
src/translate.py
src/translator_fingerspelling.py
bsl_translator_fingerspelling-0.0.1.dist-info/LICENSE
bsl_translator_fingerspelling-0.0.1.dist-info/METADATA
bsl_translator_fingerspelling-0.0.1.dist-info/WHEEL
bsl_translator_fingerspelling-0.0.1.dist-info/top_level.txt
bsl_translator_fingerspelling-0.0.1.dist-info/RECORD
